{"W03_postgis1.qmd":[],"F2.qmd":[],"lights.qmd":[],"W05_quiz.qmd":[],"ships.qmd":[],"W8_refineries.qmd":[],"object_detection.qmd":[],"F4.qmd":[],"W1_intro.qmd":[],"W04_postgis2.qmd":[],"F1.qmd":[],"W10_ships.qmd":[],"W02_SQL.qmd":[],"W08_ISM.qmd":[],"W9_blast.qmd":["borzou","borzou"],"W7_RS_data.qmd":[],"F5.qmd":[],"W5_quiz.qmd":[],"W09_blast.qmd":["borzou","borzou"],"ch2.qmd":[],"blast.qmd":["borzou","borzou"],"W01_intro.qmd":[],"index.qmd":["borzou","borzou"],"W4_postgis2.qmd":[],"W3_postgis1.qmd":[],"W06_RS.qmd":[],"W2_SQL.qmd":[],"W6_RS.qmd":[],"refineries.qmd":[],"W07_refineries.qmd":[],"ch1.qmd":[]}
